LICENSE.md
MANIFEST.in
README.md
pyproject.toml
rules/archive.yaml
rules/trash.yaml
salty_gmailer.egg-info/PKG-INFO
salty_gmailer.egg-info/SOURCES.txt
salty_gmailer.egg-info/dependency_links.txt
salty_gmailer.egg-info/entry_points.txt
salty_gmailer.egg-info/requires.txt
salty_gmailer.egg-info/top_level.txt
src/__init__.py
src/__main__.py
src/cli.py
src/logger.py
src/mailer.py
src/rule.py
venv/Lib/site-packages/__editable___gmailer_0_0_1_finder.py
venv/Lib/site-packages/_black_version.py
venv/Lib/site-packages/_virtualenv.py
venv/Lib/site-packages/google_auth_httplib2.py
venv/Lib/site-packages/mypy_extensions.py
venv/Lib/site-packages/py.py
venv/Lib/site-packages/six.py
venv/Lib/site-packages/_distutils_hack/__init__.py
venv/Lib/site-packages/_distutils_hack/override.py
venv/Lib/site-packages/_pytest/__init__.py
venv/Lib/site-packages/_pytest/_argcomplete.py
venv/Lib/site-packages/_pytest/_version.py
venv/Lib/site-packages/_pytest/cacheprovider.py
venv/Lib/site-packages/_pytest/capture.py
venv/Lib/site-packages/_pytest/compat.py
venv/Lib/site-packages/_pytest/debugging.py
venv/Lib/site-packages/_pytest/deprecated.py
venv/Lib/site-packages/_pytest/doctest.py
venv/Lib/site-packages/_pytest/faulthandler.py
venv/Lib/site-packages/_pytest/fixtures.py
venv/Lib/site-packages/_pytest/freeze_support.py
venv/Lib/site-packages/_pytest/helpconfig.py
venv/Lib/site-packages/_pytest/hookspec.py
venv/Lib/site-packages/_pytest/junitxml.py
venv/Lib/site-packages/_pytest/legacypath.py
venv/Lib/site-packages/_pytest/logging.py
venv/Lib/site-packages/_pytest/main.py
venv/Lib/site-packages/_pytest/monkeypatch.py
venv/Lib/site-packages/_pytest/nodes.py
venv/Lib/site-packages/_pytest/nose.py
venv/Lib/site-packages/_pytest/outcomes.py
venv/Lib/site-packages/_pytest/pastebin.py
venv/Lib/site-packages/_pytest/pathlib.py
venv/Lib/site-packages/_pytest/pytester.py
venv/Lib/site-packages/_pytest/pytester_assertions.py
venv/Lib/site-packages/_pytest/python.py
venv/Lib/site-packages/_pytest/python_api.py
venv/Lib/site-packages/_pytest/python_path.py
venv/Lib/site-packages/_pytest/recwarn.py
venv/Lib/site-packages/_pytest/reports.py
venv/Lib/site-packages/_pytest/runner.py
venv/Lib/site-packages/_pytest/scope.py
